babel_godot.py
json_extractor.py
Babel_Thrive-1.4.dist-info/LICENSE
Babel_Thrive-1.4.dist-info/METADATA
Babel_Thrive-1.4.dist-info/WHEEL
Babel_Thrive-1.4.dist-info/entry_points.txt
Babel_Thrive-1.4.dist-info/top_level.txt
Babel_Thrive-1.4.dist-info/RECORD
